{
 "hashrate1m": "227K",
 "hashrate5m": "128K",
 "hashrate1hr": "88.7K",
 "hashrate1d": "49.1K",
 "hashrate7d": "50.4K",
 "lastshare": 1764051026,
 "workers": 1,
 "shares": 644096.0,
 "bestshare": 1090.563420309137,
 "bestever": 1090.563420309137,
 "authorised": 1734028817,
 "worker": [
  {
   "workername": "[redacted]",
   "hashrate1m": "227K",
   "hashrate5m": "128K",
   "hashrate1hr": "88.7K",
   "hashrate1d": "49.1K",
   "hashrate7d": "50.4K",
   "lastshare": 1764051026,
   "shares": 644096.0,
   "bestshare": 1090.563420309137,
   "bestever": 1090.563420309137
  }
 ]
}
