{
 "hashrate1m": "41.9K",
 "hashrate5m": "39.3K",
 "hashrate1hr": "49K",
 "hashrate1d": "50.9K",
 "hashrate7d": "50.6K",
 "lastshare": 1756886818,
 "workers": 1,
 "shares": 547411.0,
 "bestshare": 1090.563420309137,
 "bestever": 1090.563420309137,
 "authorised": 1734028817,
 "worker": [
  {
   "workername": "[redacted]",
   "hashrate1m": "41.9K",
   "hashrate5m": "39.3K",
   "hashrate1hr": "49K",
   "hashrate1d": "50.9K",
   "hashrate7d": "50.6K",
   "lastshare": 1756886818,
   "shares": 547411.0,
   "bestshare": 1090.563420309137,
   "bestever": 1090.563420309137
  }
 ]
}
