{
 "hashrate1m": "57.9K",
 "hashrate5m": "62.4K",
 "hashrate1hr": "54.7K",
 "hashrate1d": "57.2K",
 "hashrate7d": "51K",
 "lastshare": 1752082203,
 "workers": 1,
 "shares": 435823.0,
 "bestshare": 1090.563420309137,
 "bestever": 1090.563420309137,
 "authorised": 1734028817,
 "worker": [
  {
   "workername": "[redacted]",
   "hashrate1m": "57.9K",
   "hashrate5m": "62.4K",
   "hashrate1hr": "54.7K",
   "hashrate1d": "57.2K",
   "hashrate7d": "51K",
   "lastshare": 1752082203,
   "shares": 435823.0,
   "bestshare": 1090.563420309137,
   "bestever": 1090.563420309137
  }
 ]
}
