{
 "hashrate1m": "179K",
 "hashrate5m": "86.2K",
 "hashrate1hr": "54.6K",
 "hashrate1d": "56.1K",
 "hashrate7d": "53.3K",
 "lastshare": 1768822046,
 "workers": 1,
 "shares": 702539.0,
 "bestshare": 1090.563420309137,
 "bestever": 1090.563420309137,
 "authorised": 1734028817,
 "worker": [
  {
   "workername": "[redacted]",
   "hashrate1m": "179K",
   "hashrate5m": "86.2K",
   "hashrate1hr": "54.6K",
   "hashrate1d": "56.1K",
   "hashrate7d": "53.3K",
   "lastshare": 1768822046,
   "shares": 702539.0,
   "bestshare": 1090.563420309137,
   "bestever": 1090.563420309137
  }
 ]
}
