{
 "hashrate1m": "62.9K",
 "hashrate5m": "57.6K",
 "hashrate1hr": "45K",
 "hashrate1d": "47.3K",
 "hashrate7d": "48.5K",
 "lastshare": 1754688644,
 "workers": 1,
 "shares": 495393.0,
 "bestshare": 1090.563420309137,
 "bestever": 1090.563420309137,
 "authorised": 1734028817,
 "worker": [
  {
   "workername": "[redacted]",
   "hashrate1m": "62.9K",
   "hashrate5m": "57.6K",
   "hashrate1hr": "45K",
   "hashrate1d": "47.3K",
   "hashrate7d": "48.5K",
   "lastshare": 1754688644,
   "shares": 495393.0,
   "bestshare": 1090.563420309137,
   "bestever": 1090.563420309137
  }
 ]
}
