{
 "hashrate1m": "103K",
 "hashrate5m": "58.3K",
 "hashrate1hr": "48.4K",
 "hashrate1d": "50.4K",
 "hashrate7d": "50.5K",
 "lastshare": 1755604813,
 "workers": 1,
 "shares": 517223.0,
 "bestshare": 1090.563420309137,
 "bestever": 1090.563420309137,
 "authorised": 1734028817,
 "worker": [
  {
   "workername": "[redacted]",
   "hashrate1m": "103K",
   "hashrate5m": "58.3K",
   "hashrate1hr": "48.4K",
   "hashrate1d": "50.4K",
   "hashrate7d": "50.5K",
   "lastshare": 1755604813,
   "shares": 517223.0,
   "bestshare": 1090.563420309137,
   "bestever": 1090.563420309137
  }
 ]
}
