{
 "hashrate1m": "25.7K",
 "hashrate5m": "48.6K",
 "hashrate1hr": "63.4K",
 "hashrate1d": "55.6K",
 "hashrate7d": "45.4K",
 "lastshare": 1767743730,
 "workers": 1,
 "shares": 688715.0,
 "bestshare": 1090.563420309137,
 "bestever": 1090.563420309137,
 "authorised": 1734028817,
 "worker": [
  {
   "workername": "[redacted]",
   "hashrate1m": "25.7K",
   "hashrate5m": "48.6K",
   "hashrate1hr": "63.4K",
   "hashrate1d": "55.6K",
   "hashrate7d": "45.4K",
   "lastshare": 1767743730,
   "shares": 688715.0,
   "bestshare": 1090.563420309137,
   "bestever": 1090.563420309137
  }
 ]
}
