{
 "hashrate1m": "81.6K",
 "hashrate5m": "57.7K",
 "hashrate1hr": "54.1K",
 "hashrate1d": "50.8K",
 "hashrate7d": "50.5K",
 "lastshare": 1756738485,
 "workers": 1,
 "shares": 543875.0,
 "bestshare": 1090.563420309137,
 "bestever": 1090.563420309137,
 "authorised": 1734028817,
 "worker": [
  {
   "workername": "[redacted]",
   "hashrate1m": "81.6K",
   "hashrate5m": "57.7K",
   "hashrate1hr": "54.1K",
   "hashrate1d": "50.8K",
   "hashrate7d": "50.5K",
   "lastshare": 1756738485,
   "shares": 543875.0,
   "bestshare": 1090.563420309137,
   "bestever": 1090.563420309137
  }
 ]
}
