{
 "hashrate1m": "66.4K",
 "hashrate5m": "59.6K",
 "hashrate1hr": "47.5K",
 "hashrate1d": "33.2K",
 "hashrate7d": "30.4K",
 "lastshare": 1758163547,
 "workers": 1,
 "shares": 568586.0,
 "bestshare": 1090.563420309137,
 "bestever": 1090.563420309137,
 "authorised": 1734028817,
 "worker": [
  {
   "workername": "[redacted]",
   "hashrate1m": "66.4K",
   "hashrate5m": "59.6K",
   "hashrate1hr": "47.5K",
   "hashrate1d": "33.2K",
   "hashrate7d": "30.4K",
   "lastshare": 1758163547,
   "shares": 568586.0,
   "bestshare": 1090.563420309137,
   "bestever": 1090.563420309137
  }
 ]
}
