{
 "hashrate1m": "186K",
 "hashrate5m": "88.2K",
 "hashrate1hr": "57.1K",
 "hashrate1d": "52.3K",
 "hashrate7d": "40K",
 "lastshare": 1758534027,
 "workers": 1,
 "shares": 576748.0,
 "bestshare": 1090.563420309137,
 "bestever": 1090.563420309137,
 "authorised": 1734028817,
 "worker": [
  {
   "workername": "[redacted]",
   "hashrate1m": "186K",
   "hashrate5m": "88.2K",
   "hashrate1hr": "57.1K",
   "hashrate1d": "52.3K",
   "hashrate7d": "40K",
   "lastshare": 1758534027,
   "shares": 576748.0,
   "bestshare": 1090.563420309137,
   "bestever": 1090.563420309137
  }
 ]
}
