{
 "hashrate1m": "149K",
 "hashrate5m": "83.8K",
 "hashrate1hr": "69.5K",
 "hashrate1d": "59.6K",
 "hashrate7d": "49.2K",
 "lastshare": 1754598945,
 "workers": 1,
 "shares": 493516.0,
 "bestshare": 1090.563420309137,
 "bestever": 1090.563420309137,
 "authorised": 1734028817,
 "worker": [
  {
   "workername": "[redacted]",
   "hashrate1m": "149K",
   "hashrate5m": "83.8K",
   "hashrate1hr": "69.5K",
   "hashrate1d": "59.6K",
   "hashrate7d": "49.2K",
   "lastshare": 1754598945,
   "shares": 493516.0,
   "bestshare": 1090.563420309137,
   "bestever": 1090.563420309137
  }
 ]
}
