{
 "hashrate1m": "116K",
 "hashrate5m": "68.5K",
 "hashrate1hr": "60.9K",
 "hashrate1d": "71.4K",
 "hashrate7d": "66.7K",
 "lastshare": 1764883884,
 "workers": 1,
 "shares": 658186.0,
 "bestshare": 1090.563420309137,
 "bestever": 1090.563420309137,
 "authorised": 1734028817,
 "worker": [
  {
   "workername": "[redacted]",
   "hashrate1m": "116K",
   "hashrate5m": "68.5K",
   "hashrate1hr": "60.9K",
   "hashrate1d": "71.4K",
   "hashrate7d": "66.7K",
   "lastshare": 1764883884,
   "shares": 658186.0,
   "bestshare": 1090.563420309137,
   "bestever": 1090.563420309137
  }
 ]
}
