{
 "hashrate1m": "66.8K",
 "hashrate5m": "52.5K",
 "hashrate1hr": "51.9K",
 "hashrate1d": "50.5K",
 "hashrate7d": "51.2K",
 "lastshare": 1753299323,
 "workers": 1,
 "shares": 464772.0,
 "bestshare": 1090.563420309137,
 "bestever": 1090.563420309137,
 "authorised": 1734028817,
 "worker": [
  {
   "workername": "[redacted]",
   "hashrate1m": "66.8K",
   "hashrate5m": "52.5K",
   "hashrate1hr": "51.9K",
   "hashrate1d": "50.5K",
   "hashrate7d": "51.2K",
   "lastshare": 1753299323,
   "shares": 464772.0,
   "bestshare": 1090.563420309137,
   "bestever": 1090.563420309137
  }
 ]
}
