{
 "hashrate1m": "65.4K",
 "hashrate5m": "49.7K",
 "hashrate1hr": "54.9K",
 "hashrate1d": "53.4K",
 "hashrate7d": "52.6K",
 "lastshare": 1771658940,
 "workers": 1,
 "shares": 736114.0,
 "bestshare": 1090.563420309137,
 "bestever": 1090.563420309137,
 "authorised": 1734028817,
 "worker": [
  {
   "workername": "[redacted]",
   "hashrate1m": "65.4K",
   "hashrate5m": "49.7K",
   "hashrate1hr": "54.9K",
   "hashrate1d": "53.4K",
   "hashrate7d": "52.6K",
   "lastshare": 1771658940,
   "shares": 736114.0,
   "bestshare": 1090.563420309137,
   "bestever": 1090.563420309137
  }
 ]
}
