{
 "hashrate1m": "71.9K",
 "hashrate5m": "67.1K",
 "hashrate1hr": "64.2K",
 "hashrate1d": "71.6K",
 "hashrate7d": "60.3K",
 "lastshare": 1764406203,
 "workers": 1,
 "shares": 650135.0,
 "bestshare": 1090.563420309137,
 "bestever": 1090.563420309137,
 "authorised": 1734028817,
 "worker": [
  {
   "workername": "[redacted]",
   "hashrate1m": "71.9K",
   "hashrate5m": "67.1K",
   "hashrate1hr": "64.2K",
   "hashrate1d": "71.6K",
   "hashrate7d": "60.3K",
   "lastshare": 1764406203,
   "shares": 650135.0,
   "bestshare": 1090.563420309137,
   "bestever": 1090.563420309137
  }
 ]
}
