{
 "hashrate1m": "37.3K",
 "hashrate5m": "45.3K",
 "hashrate1hr": "55.7K",
 "hashrate1d": "57.5K",
 "hashrate7d": "51.1K",
 "lastshare": 1768195595,
 "workers": 1,
 "shares": 694609.0,
 "bestshare": 1090.563420309137,
 "bestever": 1090.563420309137,
 "authorised": 1734028817,
 "worker": [
  {
   "workername": "[redacted]",
   "hashrate1m": "37.3K",
   "hashrate5m": "45.3K",
   "hashrate1hr": "55.7K",
   "hashrate1d": "57.5K",
   "hashrate7d": "51.1K",
   "lastshare": 1768195595,
   "shares": 694609.0,
   "bestshare": 1090.563420309137,
   "bestever": 1090.563420309137
  }
 ]
}
