{
 "hashrate1m": "42.4K",
 "hashrate5m": "43.4K",
 "hashrate1hr": "40.6K",
 "hashrate1d": "38.9K",
 "hashrate7d": "51.2K",
 "lastshare": 1769244994,
 "workers": 1,
 "shares": 707516.0,
 "bestshare": 1090.563420309137,
 "bestever": 1090.563420309137,
 "authorised": 1734028817,
 "worker": [
  {
   "workername": "[redacted]",
   "hashrate1m": "42.4K",
   "hashrate5m": "43.4K",
   "hashrate1hr": "40.6K",
   "hashrate1d": "38.9K",
   "hashrate7d": "51.2K",
   "lastshare": 1769244994,
   "shares": 707516.0,
   "bestshare": 1090.563420309137,
   "bestever": 1090.563420309137
  }
 ]
}
