{
 "hashrate1m": "51.1K",
 "hashrate5m": "53.4K",
 "hashrate1hr": "56.8K",
 "hashrate1d": "45.8K",
 "hashrate7d": "46.8K",
 "lastshare": 1754021120,
 "workers": 1,
 "shares": 480343.0,
 "bestshare": 1090.563420309137,
 "bestever": 1090.563420309137,
 "authorised": 1734028817,
 "worker": [
  {
   "workername": "[redacted]",
   "hashrate1m": "51.1K",
   "hashrate5m": "53.4K",
   "hashrate1hr": "56.8K",
   "hashrate1d": "45.8K",
   "hashrate7d": "46.8K",
   "lastshare": 1754021120,
   "shares": 480343.0,
   "bestshare": 1090.563420309137,
   "bestever": 1090.563420309137
  }
 ]
}
