{
 "hashrate1m": "161K",
 "hashrate5m": "138K",
 "hashrate1hr": "70.6K",
 "hashrate1d": "55.5K",
 "hashrate7d": "54.6K",
 "lastshare": 1761515113,
 "workers": 1,
 "shares": 613424.0,
 "bestshare": 1090.563420309137,
 "bestever": 1090.563420309137,
 "authorised": 1734028817,
 "worker": [
  {
   "workername": "[redacted]",
   "hashrate1m": "161K",
   "hashrate5m": "138K",
   "hashrate1hr": "70.6K",
   "hashrate1d": "55.5K",
   "hashrate7d": "54.6K",
   "lastshare": 1761515113,
   "shares": 613424.0,
   "bestshare": 1090.563420309137,
   "bestever": 1090.563420309137
  }
 ]
}
