{
 "hashrate1m": "67.2K",
 "hashrate5m": "63.1K",
 "hashrate1hr": "50.5K",
 "hashrate1d": "32.9K",
 "hashrate7d": "30.3K",
 "lastshare": 1758160451,
 "workers": 1,
 "shares": 568526.0,
 "bestshare": 1090.563420309137,
 "bestever": 1090.563420309137,
 "authorised": 1734028817,
 "worker": [
  {
   "workername": "[redacted]",
   "hashrate1m": "67.2K",
   "hashrate5m": "63.1K",
   "hashrate1hr": "50.5K",
   "hashrate1d": "32.9K",
   "hashrate7d": "30.3K",
   "lastshare": 1758160451,
   "shares": 568526.0,
   "bestshare": 1090.563420309137,
   "bestever": 1090.563420309137
  }
 ]
}
