{
 "hashrate1m": "61.4K",
 "hashrate5m": "65.7K",
 "hashrate1hr": "57.6K",
 "hashrate1d": "54.2K",
 "hashrate7d": "49.7K",
 "lastshare": 1768101967,
 "workers": 1,
 "shares": 693315.0,
 "bestshare": 1090.563420309137,
 "bestever": 1090.563420309137,
 "authorised": 1734028817,
 "worker": [
  {
   "workername": "[redacted]",
   "hashrate1m": "61.4K",
   "hashrate5m": "65.7K",
   "hashrate1hr": "57.6K",
   "hashrate1d": "54.2K",
   "hashrate7d": "49.7K",
   "lastshare": 1768101967,
   "shares": 693315.0,
   "bestshare": 1090.563420309137,
   "bestever": 1090.563420309137
  }
 ]
}
