{
 "hashrate1m": "130K",
 "hashrate5m": "95.7K",
 "hashrate1hr": "64.1K",
 "hashrate1d": "55.4K",
 "hashrate7d": "52K",
 "lastshare": 1760316135,
 "workers": 1,
 "shares": 598260.0,
 "bestshare": 1090.563420309137,
 "bestever": 1090.563420309137,
 "authorised": 1734028817,
 "worker": [
  {
   "workername": "[redacted]",
   "hashrate1m": "130K",
   "hashrate5m": "95.7K",
   "hashrate1hr": "64.1K",
   "hashrate1d": "55.4K",
   "hashrate7d": "52K",
   "lastshare": 1760316135,
   "shares": 598260.0,
   "bestshare": 1090.563420309137,
   "bestever": 1090.563420309137
  }
 ]
}
