{
 "hashrate1m": "83.5K",
 "hashrate5m": "55.7K",
 "hashrate1hr": "51.4K",
 "hashrate1d": "51.6K",
 "hashrate7d": "51.1K",
 "lastshare": 1757604488,
 "workers": 1,
 "shares": 564459.0,
 "bestshare": 1090.563420309137,
 "bestever": 1090.563420309137,
 "authorised": 1734028817,
 "worker": [
  {
   "workername": "[redacted]",
   "hashrate1m": "83.5K",
   "hashrate5m": "55.7K",
   "hashrate1hr": "51.4K",
   "hashrate1d": "51.6K",
   "hashrate7d": "51.1K",
   "lastshare": 1757604488,
   "shares": 564459.0,
   "bestshare": 1090.563420309137,
   "bestever": 1090.563420309137
  }
 ]
}
