{
 "hashrate1m": "103K",
 "hashrate5m": "67.6K",
 "hashrate1hr": "61.1K",
 "hashrate1d": "54.8K",
 "hashrate7d": "54.8K",
 "lastshare": 1762096288,
 "workers": 1,
 "shares": 620896.0,
 "bestshare": 1090.563420309137,
 "bestever": 1090.563420309137,
 "authorised": 1734028817,
 "worker": [
  {
   "workername": "[redacted]",
   "hashrate1m": "103K",
   "hashrate5m": "67.6K",
   "hashrate1hr": "61.1K",
   "hashrate1d": "54.8K",
   "hashrate7d": "54.8K",
   "lastshare": 1762096288,
   "shares": 620896.0,
   "bestshare": 1090.563420309137,
   "bestever": 1090.563420309137
  }
 ]
}
