{
 "hashrate1m": "634",
 "hashrate5m": "11.1K",
 "hashrate1hr": "49.2K",
 "hashrate1d": "55.3K",
 "hashrate7d": "51K",
 "lastshare": 1760136940,
 "workers": 1,
 "shares": 595973.0,
 "bestshare": 1090.563420309137,
 "bestever": 1090.563420309137,
 "authorised": 1734028817,
 "worker": [
  {
   "workername": "[redacted]",
   "hashrate1m": "634",
   "hashrate5m": "11.1K",
   "hashrate1hr": "49.2K",
   "hashrate1d": "55.3K",
   "hashrate7d": "51K",
   "lastshare": 1760136940,
   "shares": 595973.0,
   "bestshare": 1090.563420309137,
   "bestever": 1090.563420309137
  }
 ]
}
