{
 "hashrate1m": "90.1K",
 "hashrate5m": "83.8K",
 "hashrate1hr": "60.4K",
 "hashrate1d": "54.8K",
 "hashrate7d": "61.3K",
 "lastshare": 1765546185,
 "workers": 1,
 "shares": 667519.0,
 "bestshare": 1090.563420309137,
 "bestever": 1090.563420309137,
 "authorised": 1734028817,
 "worker": [
  {
   "workername": "[redacted]",
   "hashrate1m": "90.1K",
   "hashrate5m": "83.8K",
   "hashrate1hr": "60.4K",
   "hashrate1d": "54.8K",
   "hashrate7d": "61.3K",
   "lastshare": 1765546185,
   "shares": 667519.0,
   "bestshare": 1090.563420309137,
   "bestever": 1090.563420309137
  }
 ]
}
