{
 "hashrate1m": "178K",
 "hashrate5m": "106K",
 "hashrate1hr": "56.1K",
 "hashrate1d": "53.5K",
 "hashrate7d": "38.7K",
 "lastshare": 1767418504,
 "workers": 1,
 "shares": 684580.0,
 "bestshare": 1090.563420309137,
 "bestever": 1090.563420309137,
 "authorised": 1734028817,
 "worker": [
  {
   "workername": "[redacted]",
   "hashrate1m": "178K",
   "hashrate5m": "106K",
   "hashrate1hr": "56.1K",
   "hashrate1d": "53.5K",
   "hashrate7d": "38.7K",
   "lastshare": 1767418504,
   "shares": 684580.0,
   "bestshare": 1090.563420309137,
   "bestever": 1090.563420309137
  }
 ]
}
