{
 "hashrate1m": "50.3K",
 "hashrate5m": "47.1K",
 "hashrate1hr": "49.2K",
 "hashrate1d": "50.9K",
 "hashrate7d": "50.8K",
 "lastshare": 1752569242,
 "workers": 1,
 "shares": 447303.0,
 "bestshare": 1090.563420309137,
 "bestever": 1090.563420309137,
 "authorised": 1734028817,
 "worker": [
  {
   "workername": "[redacted]",
   "hashrate1m": "50.3K",
   "hashrate5m": "47.1K",
   "hashrate1hr": "49.2K",
   "hashrate1d": "50.9K",
   "hashrate7d": "50.8K",
   "lastshare": 1752569242,
   "shares": 447303.0,
   "bestshare": 1090.563420309137,
   "bestever": 1090.563420309137
  }
 ]
}
