{
 "hashrate1m": "51.2K",
 "hashrate5m": "46.8K",
 "hashrate1hr": "50.6K",
 "hashrate1d": "16.6K",
 "hashrate7d": "30.9K",
 "lastshare": 1751529624,
 "workers": 1,
 "shares": 418964.0,
 "bestshare": 1090.563420309137,
 "bestever": 1090.563420309137,
 "authorised": 1734028817,
 "worker": [
  {
   "workername": "[redacted]",
   "hashrate1m": "51.2K",
   "hashrate5m": "46.8K",
   "hashrate1hr": "50.6K",
   "hashrate1d": "16.6K",
   "hashrate7d": "30.9K",
   "lastshare": 1751529624,
   "shares": 418964.0,
   "bestshare": 1090.563420309137,
   "bestever": 1090.563420309137
  }
 ]
}
