{
 "hashrate1m": "156K",
 "hashrate5m": "85K",
 "hashrate1hr": "59.2K",
 "hashrate1d": "54.8K",
 "hashrate7d": "50.3K",
 "lastshare": 1759285947,
 "workers": 1,
 "shares": 586245.0,
 "bestshare": 1090.563420309137,
 "bestever": 1090.563420309137,
 "authorised": 1734028817,
 "worker": [
  {
   "workername": "[redacted]",
   "hashrate1m": "156K",
   "hashrate5m": "85K",
   "hashrate1hr": "59.2K",
   "hashrate1d": "54.8K",
   "hashrate7d": "50.3K",
   "lastshare": 1759285947,
   "shares": 586245.0,
   "bestshare": 1090.563420309137,
   "bestever": 1090.563420309137
  }
 ]
}
