{
 "hashrate1m": "49.7K",
 "hashrate5m": "48.3K",
 "hashrate1hr": "51.1K",
 "hashrate1d": "41.7K",
 "hashrate7d": "48.4K",
 "lastshare": 1770270111,
 "workers": 1,
 "shares": 719185.0,
 "bestshare": 1090.563420309137,
 "bestever": 1090.563420309137,
 "authorised": 1734028817,
 "worker": [
  {
   "workername": "[redacted]",
   "hashrate1m": "49.7K",
   "hashrate5m": "48.3K",
   "hashrate1hr": "51.1K",
   "hashrate1d": "41.7K",
   "hashrate7d": "48.4K",
   "lastshare": 1770270111,
   "shares": 719185.0,
   "bestshare": 1090.563420309137,
   "bestever": 1090.563420309137
  }
 ]
}
