{
 "hashrate1m": "52.9K",
 "hashrate5m": "40K",
 "hashrate1hr": "48.1K",
 "hashrate1d": "51.2K",
 "hashrate7d": "50.8K",
 "lastshare": 1757423009,
 "workers": 1,
 "shares": 560064.0,
 "bestshare": 1090.563420309137,
 "bestever": 1090.563420309137,
 "authorised": 1734028817,
 "worker": [
  {
   "workername": "[redacted]",
   "hashrate1m": "52.9K",
   "hashrate5m": "40K",
   "hashrate1hr": "48.1K",
   "hashrate1d": "51.2K",
   "hashrate7d": "50.8K",
   "lastshare": 1757423009,
   "shares": 560064.0,
   "bestshare": 1090.563420309137,
   "bestever": 1090.563420309137
  }
 ]
}
