{
 "hashrate1m": "82.9K",
 "hashrate5m": "73.5K",
 "hashrate1hr": "49.8K",
 "hashrate1d": "55.2K",
 "hashrate7d": "63.6K",
 "lastshare": 1765365631,
 "workers": 1,
 "shares": 665218.0,
 "bestshare": 1090.563420309137,
 "bestever": 1090.563420309137,
 "authorised": 1734028817,
 "worker": [
  {
   "workername": "[redacted]",
   "hashrate1m": "82.9K",
   "hashrate5m": "73.5K",
   "hashrate1hr": "49.8K",
   "hashrate1d": "55.2K",
   "hashrate7d": "63.6K",
   "lastshare": 1765365631,
   "shares": 665218.0,
   "bestshare": 1090.563420309137,
   "bestever": 1090.563420309137
  }
 ]
}
