{
 "hashrate1m": "29.1K",
 "hashrate5m": "40.5K",
 "hashrate1hr": "58K",
 "hashrate1d": "56.7K",
 "hashrate7d": "55.3K",
 "lastshare": 1761851021,
 "workers": 1,
 "shares": 617820.0,
 "bestshare": 1090.563420309137,
 "bestever": 1090.563420309137,
 "authorised": 1734028817,
 "worker": [
  {
   "workername": "[redacted]",
   "hashrate1m": "29.1K",
   "hashrate5m": "40.5K",
   "hashrate1hr": "58K",
   "hashrate1d": "56.7K",
   "hashrate7d": "55.3K",
   "lastshare": 1761851021,
   "shares": 617820.0,
   "bestshare": 1090.563420309137,
   "bestever": 1090.563420309137
  }
 ]
}
