{
 "hashrate1m": "114K",
 "hashrate5m": "83.1K",
 "hashrate1hr": "57K",
 "hashrate1d": "44.1K",
 "hashrate7d": "49.2K",
 "lastshare": 1770234889,
 "workers": 1,
 "shares": 718887.0,
 "bestshare": 1090.563420309137,
 "bestever": 1090.563420309137,
 "authorised": 1734028817,
 "worker": [
  {
   "workername": "[redacted]",
   "hashrate1m": "114K",
   "hashrate5m": "83.1K",
   "hashrate1hr": "57K",
   "hashrate1d": "44.1K",
   "hashrate7d": "49.2K",
   "lastshare": 1770234889,
   "shares": 718887.0,
   "bestshare": 1090.563420309137,
   "bestever": 1090.563420309137
  }
 ]
}
