{
 "hashrate1m": "25.7K",
 "hashrate5m": "32.9K",
 "hashrate1hr": "52.2K",
 "hashrate1d": "55K",
 "hashrate7d": "54.4K",
 "lastshare": 1772671015,
 "workers": 1,
 "shares": 749057.0,
 "bestshare": 1090.563420309137,
 "bestever": 1090.563420309137,
 "authorised": 1734028817,
 "worker": [
  {
   "workername": "[redacted]",
   "hashrate1m": "25.7K",
   "hashrate5m": "32.9K",
   "hashrate1hr": "52.2K",
   "hashrate1d": "55K",
   "hashrate7d": "54.4K",
   "lastshare": 1772671015,
   "shares": 749057.0,
   "bestshare": 1090.563420309137,
   "bestever": 1090.563420309137
  }
 ]
}
