{
 "hashrate1m": "70.9K",
 "hashrate5m": "63.9K",
 "hashrate1hr": "57.3K",
 "hashrate1d": "47.5K",
 "hashrate7d": "47.1K",
 "lastshare": 1754043444,
 "workers": 1,
 "shares": 480895.0,
 "bestshare": 1090.563420309137,
 "bestever": 1090.563420309137,
 "authorised": 1734028817,
 "worker": [
  {
   "workername": "[redacted]",
   "hashrate1m": "70.9K",
   "hashrate5m": "63.9K",
   "hashrate1hr": "57.3K",
   "hashrate1d": "47.5K",
   "hashrate7d": "47.1K",
   "lastshare": 1754043444,
   "shares": 480895.0,
   "bestshare": 1090.563420309137,
   "bestever": 1090.563420309137
  }
 ]
}
