{
 "hashrate1m": "93.3K",
 "hashrate5m": "68.3K",
 "hashrate1hr": "66K",
 "hashrate1d": "66.2K",
 "hashrate7d": "52.7K",
 "lastshare": 1763555495,
 "workers": 1,
 "shares": 638130.0,
 "bestshare": 1090.563420309137,
 "bestever": 1090.563420309137,
 "authorised": 1734028817,
 "worker": [
  {
   "workername": "[redacted]",
   "hashrate1m": "93.3K",
   "hashrate5m": "68.3K",
   "hashrate1hr": "66K",
   "hashrate1d": "66.2K",
   "hashrate7d": "52.7K",
   "lastshare": 1763555495,
   "shares": 638130.0,
   "bestshare": 1090.563420309137,
   "bestever": 1090.563420309137
  }
 ]
}
