{
 "hashrate1m": "152K",
 "hashrate5m": "109K",
 "hashrate1hr": "62.2K",
 "hashrate1d": "57.1K",
 "hashrate7d": "50.5K",
 "lastshare": 1760062820,
 "workers": 1,
 "shares": 595027.0,
 "bestshare": 1090.563420309137,
 "bestever": 1090.563420309137,
 "authorised": 1734028817,
 "worker": [
  {
   "workername": "[redacted]",
   "hashrate1m": "152K",
   "hashrate5m": "109K",
   "hashrate1hr": "62.2K",
   "hashrate1d": "57.1K",
   "hashrate7d": "50.5K",
   "lastshare": 1760062820,
   "shares": 595027.0,
   "bestshare": 1090.563420309137,
   "bestever": 1090.563420309137
  }
 ]
}
