{
 "hashrate1m": "4.07K",
 "hashrate5m": "25K",
 "hashrate1hr": "51.6K",
 "hashrate1d": "53.6K",
 "hashrate7d": "52.6K",
 "lastshare": 1771596329,
 "workers": 1,
 "shares": 735355.0,
 "bestshare": 1090.563420309137,
 "bestever": 1090.563420309137,
 "authorised": 1734028817,
 "worker": [
  {
   "workername": "[redacted]",
   "hashrate1m": "4.07K",
   "hashrate5m": "25K",
   "hashrate1hr": "51.6K",
   "hashrate1d": "53.6K",
   "hashrate7d": "52.6K",
   "lastshare": 1771596329,
   "shares": 735355.0,
   "bestshare": 1090.563420309137,
   "bestever": 1090.563420309137
  }
 ]
}
