{
 "hashrate1m": "4.48K",
 "hashrate5m": "17.9K",
 "hashrate1hr": "43.7K",
 "hashrate1d": "54.5K",
 "hashrate7d": "51.6K",
 "lastshare": 1762676004,
 "workers": 1,
 "shares": 627397.0,
 "bestshare": 1090.563420309137,
 "bestever": 1090.563420309137,
 "authorised": 1734028817,
 "worker": [
  {
   "workername": "[redacted]",
   "hashrate1m": "4.48K",
   "hashrate5m": "17.9K",
   "hashrate1hr": "43.7K",
   "hashrate1d": "54.5K",
   "hashrate7d": "51.6K",
   "lastshare": 1762676004,
   "shares": 627397.0,
   "bestshare": 1090.563420309137,
   "bestever": 1090.563420309137
  }
 ]
}
