{
 "hashrate1m": "65.9K",
 "hashrate5m": "65K",
 "hashrate1hr": "64.5K",
 "hashrate1d": "56K",
 "hashrate7d": "49.3K",
 "lastshare": 1759951058,
 "workers": 1,
 "shares": 593558.0,
 "bestshare": 1090.563420309137,
 "bestever": 1090.563420309137,
 "authorised": 1734028817,
 "worker": [
  {
   "workername": "[redacted]",
   "hashrate1m": "65.9K",
   "hashrate5m": "65K",
   "hashrate1hr": "64.5K",
   "hashrate1d": "56K",
   "hashrate7d": "49.3K",
   "lastshare": 1759951058,
   "shares": 593558.0,
   "bestshare": 1090.563420309137,
   "bestever": 1090.563420309137
  }
 ]
}
