{
 "hashrate1m": "71.4K",
 "hashrate5m": "42.9K",
 "hashrate1hr": "49.6K",
 "hashrate1d": "49.8K",
 "hashrate7d": "50.3K",
 "lastshare": 1756093170,
 "workers": 1,
 "shares": 528650.0,
 "bestshare": 1090.563420309137,
 "bestever": 1090.563420309137,
 "authorised": 1734028817,
 "worker": [
  {
   "workername": "[redacted]",
   "hashrate1m": "71.4K",
   "hashrate5m": "42.9K",
   "hashrate1hr": "49.6K",
   "hashrate1d": "49.8K",
   "hashrate7d": "50.3K",
   "lastshare": 1756093170,
   "shares": 528650.0,
   "bestshare": 1090.563420309137,
   "bestever": 1090.563420309137
  }
 ]
}
