{
 "hashrate1m": "109K",
 "hashrate5m": "71.2K",
 "hashrate1hr": "52.1K",
 "hashrate1d": "46.1K",
 "hashrate7d": "45.6K",
 "lastshare": 1754287155,
 "workers": 1,
 "shares": 485697.0,
 "bestshare": 1090.563420309137,
 "bestever": 1090.563420309137,
 "authorised": 1734028817,
 "worker": [
  {
   "workername": "[redacted]",
   "hashrate1m": "109K",
   "hashrate5m": "71.2K",
   "hashrate1hr": "52.1K",
   "hashrate1d": "46.1K",
   "hashrate7d": "45.6K",
   "lastshare": 1754287155,
   "shares": 485697.0,
   "bestshare": 1090.563420309137,
   "bestever": 1090.563420309137
  }
 ]
}
