{
 "hashrate1m": "46.6K",
 "hashrate5m": "51K",
 "hashrate1hr": "50.2K",
 "hashrate1d": "52.1K",
 "hashrate7d": "51.3K",
 "lastshare": 1753070918,
 "workers": 1,
 "shares": 459354.0,
 "bestshare": 1090.563420309137,
 "bestever": 1090.563420309137,
 "authorised": 1734028817,
 "worker": [
  {
   "workername": "[redacted]",
   "hashrate1m": "46.6K",
   "hashrate5m": "51K",
   "hashrate1hr": "50.2K",
   "hashrate1d": "52.1K",
   "hashrate7d": "51.3K",
   "lastshare": 1753070918,
   "shares": 459354.0,
   "bestshare": 1090.563420309137,
   "bestever": 1090.563420309137
  }
 ]
}
