{
 "hashrate1m": "72.6K",
 "hashrate5m": "73.7K",
 "hashrate1hr": "71.4K",
 "hashrate1d": "67.2K",
 "hashrate7d": "42.8K",
 "lastshare": 1751760273,
 "workers": 1,
 "shares": 426247.0,
 "bestshare": 1090.563420309137,
 "bestever": 1090.563420309137,
 "authorised": 1734028817,
 "worker": [
  {
   "workername": "[redacted]",
   "hashrate1m": "72.6K",
   "hashrate5m": "73.7K",
   "hashrate1hr": "71.4K",
   "hashrate1d": "67.2K",
   "hashrate7d": "42.8K",
   "lastshare": 1751760273,
   "shares": 426247.0,
   "bestshare": 1090.563420309137,
   "bestever": 1090.563420309137
  }
 ]
}
