{
 "hashrate1m": "87.4K",
 "hashrate5m": "52.3K",
 "hashrate1hr": "57.3K",
 "hashrate1d": "52.9K",
 "hashrate7d": "49.8K",
 "lastshare": 1770393806,
 "workers": 1,
 "shares": 720784.0,
 "bestshare": 1090.563420309137,
 "bestever": 1090.563420309137,
 "authorised": 1734028817,
 "worker": [
  {
   "workername": "[redacted]",
   "hashrate1m": "87.4K",
   "hashrate5m": "52.3K",
   "hashrate1hr": "57.3K",
   "hashrate1d": "52.9K",
   "hashrate7d": "49.8K",
   "lastshare": 1770393806,
   "shares": 720784.0,
   "bestshare": 1090.563420309137,
   "bestever": 1090.563420309137
  }
 ]
}
