{
 "hashrate1m": "107K",
 "hashrate5m": "75.7K",
 "hashrate1hr": "50.4K",
 "hashrate1d": "52.9K",
 "hashrate7d": "52.5K",
 "lastshare": 1771664904,
 "workers": 1,
 "shares": 736178.0,
 "bestshare": 1090.563420309137,
 "bestever": 1090.563420309137,
 "authorised": 1734028817,
 "worker": [
  {
   "workername": "[redacted]",
   "hashrate1m": "107K",
   "hashrate5m": "75.7K",
   "hashrate1hr": "50.4K",
   "hashrate1d": "52.9K",
   "hashrate7d": "52.5K",
   "lastshare": 1771664904,
   "shares": 736178.0,
   "bestshare": 1090.563420309137,
   "bestever": 1090.563420309137
  }
 ]
}
