{
 "hashrate1m": "35.6K",
 "hashrate5m": "35.4K",
 "hashrate1hr": "54.1K",
 "hashrate1d": "54.7K",
 "hashrate7d": "46.9K",
 "lastshare": 1767863316,
 "workers": 1,
 "shares": 690226.0,
 "bestshare": 1090.563420309137,
 "bestever": 1090.563420309137,
 "authorised": 1734028817,
 "worker": [
  {
   "workername": "[redacted]",
   "hashrate1m": "35.6K",
   "hashrate5m": "35.4K",
   "hashrate1hr": "54.1K",
   "hashrate1d": "54.7K",
   "hashrate7d": "46.9K",
   "lastshare": 1767863316,
   "shares": 690226.0,
   "bestshare": 1090.563420309137,
   "bestever": 1090.563420309137
  }
 ]
}
