{
 "hashrate1m": "86.6K",
 "hashrate5m": "52.3K",
 "hashrate1hr": "52.2K",
 "hashrate1d": "55K",
 "hashrate7d": "51.3K",
 "lastshare": 1759429536,
 "workers": 1,
 "shares": 588093.0,
 "bestshare": 1090.563420309137,
 "bestever": 1090.563420309137,
 "authorised": 1734028817,
 "worker": [
  {
   "workername": "[redacted]",
   "hashrate1m": "86.6K",
   "hashrate5m": "52.3K",
   "hashrate1hr": "52.2K",
   "hashrate1d": "55K",
   "hashrate7d": "51.3K",
   "lastshare": 1759429536,
   "shares": 588093.0,
   "bestshare": 1090.563420309137,
   "bestever": 1090.563420309137
  }
 ]
}
