{
 "hashrate1m": "123K",
 "hashrate5m": "75.4K",
 "hashrate1hr": "75.9K",
 "hashrate1d": "70.6K",
 "hashrate7d": "48.9K",
 "lastshare": 1751908976,
 "workers": 1,
 "shares": 431153.0,
 "bestshare": 1090.563420309137,
 "bestever": 1090.563420309137,
 "authorised": 1734028817,
 "worker": [
  {
   "workername": "[redacted]",
   "hashrate1m": "123K",
   "hashrate5m": "75.4K",
   "hashrate1hr": "75.9K",
   "hashrate1d": "70.6K",
   "hashrate7d": "48.9K",
   "lastshare": 1751908976,
   "shares": 431153.0,
   "bestshare": 1090.563420309137,
   "bestever": 1090.563420309137
  }
 ]
}
