{
 "hashrate1m": "65.9K",
 "hashrate5m": "62K",
 "hashrate1hr": "50.2K",
 "hashrate1d": "49.9K",
 "hashrate7d": "50.4K",
 "lastshare": 1757100151,
 "workers": 1,
 "shares": 552368.0,
 "bestshare": 1090.563420309137,
 "bestever": 1090.563420309137,
 "authorised": 1734028817,
 "worker": [
  {
   "workername": "[redacted]",
   "hashrate1m": "65.9K",
   "hashrate5m": "62K",
   "hashrate1hr": "50.2K",
   "hashrate1d": "49.9K",
   "hashrate7d": "50.4K",
   "lastshare": 1757100151,
   "shares": 552368.0,
   "bestshare": 1090.563420309137,
   "bestever": 1090.563420309137
  }
 ]
}
