{
 "hashrate1m": "23K",
 "hashrate5m": "57.7K",
 "hashrate1hr": "68K",
 "hashrate1d": "55.5K",
 "hashrate7d": "54.9K",
 "lastshare": 1762099707,
 "workers": 1,
 "shares": 620956.0,
 "bestshare": 1090.563420309137,
 "bestever": 1090.563420309137,
 "authorised": 1734028817,
 "worker": [
  {
   "workername": "[redacted]",
   "hashrate1m": "23K",
   "hashrate5m": "57.7K",
   "hashrate1hr": "68K",
   "hashrate1d": "55.5K",
   "hashrate7d": "54.9K",
   "lastshare": 1762099707,
   "shares": 620956.0,
   "bestshare": 1090.563420309137,
   "bestever": 1090.563420309137
  }
 ]
}
