{
 "hashrate1m": "145K",
 "hashrate5m": "95.8K",
 "hashrate1hr": "68.5K",
 "hashrate1d": "25K",
 "hashrate7d": "46.1K",
 "lastshare": 1763384463,
 "workers": 1,
 "shares": 635229.0,
 "bestshare": 1090.563420309137,
 "bestever": 1090.563420309137,
 "authorised": 1734028817,
 "worker": [
  {
   "workername": "[redacted]",
   "hashrate1m": "145K",
   "hashrate5m": "95.8K",
   "hashrate1hr": "68.5K",
   "hashrate1d": "25K",
   "hashrate7d": "46.1K",
   "lastshare": 1763384463,
   "shares": 635229.0,
   "bestshare": 1090.563420309137,
   "bestever": 1090.563420309137
  }
 ]
}
