{
 "hashrate1m": "32.1K",
 "hashrate5m": "39.5K",
 "hashrate1hr": "46.3K",
 "hashrate1d": "49.2K",
 "hashrate7d": "50.1K",
 "lastshare": 1756250081,
 "workers": 1,
 "shares": 532288.0,
 "bestshare": 1090.563420309137,
 "bestever": 1090.563420309137,
 "authorised": 1734028817,
 "worker": [
  {
   "workername": "[redacted]",
   "hashrate1m": "32.1K",
   "hashrate5m": "39.5K",
   "hashrate1hr": "46.3K",
   "hashrate1d": "49.2K",
   "hashrate7d": "50.1K",
   "lastshare": 1756250081,
   "shares": 532288.0,
   "bestshare": 1090.563420309137,
   "bestever": 1090.563420309137
  }
 ]
}
