{
 "hashrate1m": "50.2K",
 "hashrate5m": "51.4K",
 "hashrate1hr": "51.3K",
 "hashrate1d": "52.3K",
 "hashrate7d": "51.3K",
 "lastshare": 1757667001,
 "workers": 1,
 "shares": 566006.0,
 "bestshare": 1090.563420309137,
 "bestever": 1090.563420309137,
 "authorised": 1734028817,
 "worker": [
  {
   "workername": "[redacted]",
   "hashrate1m": "50.2K",
   "hashrate5m": "51.4K",
   "hashrate1hr": "51.3K",
   "hashrate1d": "52.3K",
   "hashrate7d": "51.3K",
   "lastshare": 1757667001,
   "shares": 566006.0,
   "bestshare": 1090.563420309137,
   "bestever": 1090.563420309137
  }
 ]
}
