{
 "hashrate1m": "90.5K",
 "hashrate5m": "55.7K",
 "hashrate1hr": "55.4K",
 "hashrate1d": "55.3K",
 "hashrate7d": "50K",
 "lastshare": 1768127177,
 "workers": 1,
 "shares": 693658.0,
 "bestshare": 1090.563420309137,
 "bestever": 1090.563420309137,
 "authorised": 1734028817,
 "worker": [
  {
   "workername": "[redacted]",
   "hashrate1m": "90.5K",
   "hashrate5m": "55.7K",
   "hashrate1hr": "55.4K",
   "hashrate1d": "55.3K",
   "hashrate7d": "50K",
   "lastshare": 1768127177,
   "shares": 693658.0,
   "bestshare": 1090.563420309137,
   "bestever": 1090.563420309137
  }
 ]
}
