{
 "hashrate1m": "107K",
 "hashrate5m": "70.8K",
 "hashrate1hr": "60.4K",
 "hashrate1d": "55.9K",
 "hashrate7d": "55K",
 "lastshare": 1761772466,
 "workers": 1,
 "shares": 616771.0,
 "bestshare": 1090.563420309137,
 "bestever": 1090.563420309137,
 "authorised": 1734028817,
 "worker": [
  {
   "workername": "[redacted]",
   "hashrate1m": "107K",
   "hashrate5m": "70.8K",
   "hashrate1hr": "60.4K",
   "hashrate1d": "55.9K",
   "hashrate7d": "55K",
   "lastshare": 1761772466,
   "shares": 616771.0,
   "bestshare": 1090.563420309137,
   "bestever": 1090.563420309137
  }
 ]
}
