{
 "hashrate1m": "65.1K",
 "hashrate5m": "63.1K",
 "hashrate1hr": "57.9K",
 "hashrate1d": "56.7K",
 "hashrate7d": "52.6K",
 "lastshare": 1760746754,
 "workers": 1,
 "shares": 603539.0,
 "bestshare": 1090.563420309137,
 "bestever": 1090.563420309137,
 "authorised": 1734028817,
 "worker": [
  {
   "workername": "[redacted]",
   "hashrate1m": "65.1K",
   "hashrate5m": "63.1K",
   "hashrate1hr": "57.9K",
   "hashrate1d": "56.7K",
   "hashrate7d": "52.6K",
   "lastshare": 1760746754,
   "shares": 603539.0,
   "bestshare": 1090.563420309137,
   "bestever": 1090.563420309137
  }
 ]
}
