{
 "hashrate1m": "62.1K",
 "hashrate5m": "56.9K",
 "hashrate1hr": "51.3K",
 "hashrate1d": "43K",
 "hashrate7d": "46.6K",
 "lastshare": 1753985163,
 "workers": 1,
 "shares": 479489.0,
 "bestshare": 1090.563420309137,
 "bestever": 1090.563420309137,
 "authorised": 1734028817,
 "worker": [
  {
   "workername": "[redacted]",
   "hashrate1m": "62.1K",
   "hashrate5m": "56.9K",
   "hashrate1hr": "51.3K",
   "hashrate1d": "43K",
   "hashrate7d": "46.6K",
   "lastshare": 1753985163,
   "shares": 479489.0,
   "bestshare": 1090.563420309137,
   "bestever": 1090.563420309137
  }
 ]
}
