{
 "hashrate1m": "159K",
 "hashrate5m": "73.1K",
 "hashrate1hr": "49.9K",
 "hashrate1d": "58.1K",
 "hashrate7d": "50.8K",
 "lastshare": 1752054960,
 "workers": 1,
 "shares": 435126.0,
 "bestshare": 1090.563420309137,
 "bestever": 1090.563420309137,
 "authorised": 1734028817,
 "worker": [
  {
   "workername": "[redacted]",
   "hashrate1m": "159K",
   "hashrate5m": "73.1K",
   "hashrate1hr": "49.9K",
   "hashrate1d": "58.1K",
   "hashrate7d": "50.8K",
   "lastshare": 1752054960,
   "shares": 435126.0,
   "bestshare": 1090.563420309137,
   "bestever": 1090.563420309137
  }
 ]
}
