{
 "hashrate1m": "58.3K",
 "hashrate5m": "47.1K",
 "hashrate1hr": "57.4K",
 "hashrate1d": "55.1K",
 "hashrate7d": "52.5K",
 "lastshare": 1760414003,
 "workers": 1,
 "shares": 599518.0,
 "bestshare": 1090.563420309137,
 "bestever": 1090.563420309137,
 "authorised": 1734028817,
 "worker": [
  {
   "workername": "[redacted]",
   "hashrate1m": "58.3K",
   "hashrate5m": "47.1K",
   "hashrate1hr": "57.4K",
   "hashrate1d": "55.1K",
   "hashrate7d": "52.5K",
   "lastshare": 1760414003,
   "shares": 599518.0,
   "bestshare": 1090.563420309137,
   "bestever": 1090.563420309137
  }
 ]
}
