{
 "hashrate1m": "58.4K",
 "hashrate5m": "53.3K",
 "hashrate1hr": "60.6K",
 "hashrate1d": "55.2K",
 "hashrate7d": "54.1K",
 "lastshare": 1772264285,
 "workers": 1,
 "shares": 743860.0,
 "bestshare": 1090.563420309137,
 "bestever": 1090.563420309137,
 "authorised": 1734028817,
 "worker": [
  {
   "workername": "[redacted]",
   "hashrate1m": "58.4K",
   "hashrate5m": "53.3K",
   "hashrate1hr": "60.6K",
   "hashrate1d": "55.2K",
   "hashrate7d": "54.1K",
   "lastshare": 1772264285,
   "shares": 743860.0,
   "bestshare": 1090.563420309137,
   "bestever": 1090.563420309137
  }
 ]
}
