{
 "hashrate1m": "76.4K",
 "hashrate5m": "54.6K",
 "hashrate1hr": "49.5K",
 "hashrate1d": "55K",
 "hashrate7d": "47.9K",
 "lastshare": 1759044129,
 "workers": 1,
 "shares": 583143.0,
 "bestshare": 1090.563420309137,
 "bestever": 1090.563420309137,
 "authorised": 1734028817,
 "worker": [
  {
   "workername": "[redacted]",
   "hashrate1m": "76.4K",
   "hashrate5m": "54.6K",
   "hashrate1hr": "49.5K",
   "hashrate1d": "55K",
   "hashrate7d": "47.9K",
   "lastshare": 1759044129,
   "shares": 583143.0,
   "bestshare": 1090.563420309137,
   "bestever": 1090.563420309137
  }
 ]
}
