{
 "hashrate1m": "72.6K",
 "hashrate5m": "56K",
 "hashrate1hr": "53.2K",
 "hashrate1d": "42.7K",
 "hashrate7d": "47.8K",
 "lastshare": 1770739960,
 "workers": 1,
 "shares": 724484.0,
 "bestshare": 1090.563420309137,
 "bestever": 1090.563420309137,
 "authorised": 1734028817,
 "worker": [
  {
   "workername": "[redacted]",
   "hashrate1m": "72.6K",
   "hashrate5m": "56K",
   "hashrate1hr": "53.2K",
   "hashrate1d": "42.7K",
   "hashrate7d": "47.8K",
   "lastshare": 1770739960,
   "shares": 724484.0,
   "bestshare": 1090.563420309137,
   "bestever": 1090.563420309137
  }
 ]
}
