{
 "hashrate1m": "88.4K",
 "hashrate5m": "57.7K",
 "hashrate1hr": "59.1K",
 "hashrate1d": "55.7K",
 "hashrate7d": "53.2K",
 "lastshare": 1768794111,
 "workers": 1,
 "shares": 702167.0,
 "bestshare": 1090.563420309137,
 "bestever": 1090.563420309137,
 "authorised": 1734028817,
 "worker": [
  {
   "workername": "[redacted]",
   "hashrate1m": "88.4K",
   "hashrate5m": "57.7K",
   "hashrate1hr": "59.1K",
   "hashrate1d": "55.7K",
   "hashrate7d": "53.2K",
   "lastshare": 1768794111,
   "shares": 702167.0,
   "bestshare": 1090.563420309137,
   "bestever": 1090.563420309137
  }
 ]
}
