{
 "hashrate1m": "98K",
 "hashrate5m": "70.4K",
 "hashrate1hr": "56K",
 "hashrate1d": "51K",
 "hashrate7d": "50.6K",
 "lastshare": 1756760114,
 "workers": 1,
 "shares": 544391.0,
 "bestshare": 1090.563420309137,
 "bestever": 1090.563420309137,
 "authorised": 1734028817,
 "worker": [
  {
   "workername": "[redacted]",
   "hashrate1m": "98K",
   "hashrate5m": "70.4K",
   "hashrate1hr": "56K",
   "hashrate1d": "51K",
   "hashrate7d": "50.6K",
   "lastshare": 1756760114,
   "shares": 544391.0,
   "bestshare": 1090.563420309137,
   "bestever": 1090.563420309137
  }
 ]
}
