{
 "hashrate1m": "79.8K",
 "hashrate5m": "63.4K",
 "hashrate1hr": "53.9K",
 "hashrate1d": "51.6K",
 "hashrate7d": "51.1K",
 "lastshare": 1757616377,
 "workers": 1,
 "shares": 564748.0,
 "bestshare": 1090.563420309137,
 "bestever": 1090.563420309137,
 "authorised": 1734028817,
 "worker": [
  {
   "workername": "[redacted]",
   "hashrate1m": "79.8K",
   "hashrate5m": "63.4K",
   "hashrate1hr": "53.9K",
   "hashrate1d": "51.6K",
   "hashrate7d": "51.1K",
   "lastshare": 1757616377,
   "shares": 564748.0,
   "bestshare": 1090.563420309137,
   "bestever": 1090.563420309137
  }
 ]
}
