{
 "hashrate1m": "72.8K",
 "hashrate5m": "57.7K",
 "hashrate1hr": "58.9K",
 "hashrate1d": "57.1K",
 "hashrate7d": "64.7K",
 "lastshare": 1765291259,
 "workers": 1,
 "shares": 664264.0,
 "bestshare": 1090.563420309137,
 "bestever": 1090.563420309137,
 "authorised": 1734028817,
 "worker": [
  {
   "workername": "[redacted]",
   "hashrate1m": "72.8K",
   "hashrate5m": "57.7K",
   "hashrate1hr": "58.9K",
   "hashrate1d": "57.1K",
   "hashrate7d": "64.7K",
   "lastshare": 1765291259,
   "shares": 664264.0,
   "bestshare": 1090.563420309137,
   "bestever": 1090.563420309137
  }
 ]
}
