{
 "hashrate1m": "66.8K",
 "hashrate5m": "73.5K",
 "hashrate1hr": "61.5K",
 "hashrate1d": "53.8K",
 "hashrate7d": "41.5K",
 "lastshare": 1767543671,
 "workers": 1,
 "shares": 686138.0,
 "bestshare": 1090.563420309137,
 "bestever": 1090.563420309137,
 "authorised": 1734028817,
 "worker": [
  {
   "workername": "[redacted]",
   "hashrate1m": "66.8K",
   "hashrate5m": "73.5K",
   "hashrate1hr": "61.5K",
   "hashrate1d": "53.8K",
   "hashrate7d": "41.5K",
   "lastshare": 1767543671,
   "shares": 686138.0,
   "bestshare": 1090.563420309137,
   "bestever": 1090.563420309137
  }
 ]
}
