{
 "hashrate1m": "38.5K",
 "hashrate5m": "45.6K",
 "hashrate1hr": "54.8K",
 "hashrate1d": "56K",
 "hashrate7d": "53.6K",
 "lastshare": 1771992435,
 "workers": 1,
 "shares": 740379.0,
 "bestshare": 1090.563420309137,
 "bestever": 1090.563420309137,
 "authorised": 1734028817,
 "worker": [
  {
   "workername": "[redacted]",
   "hashrate1m": "38.5K",
   "hashrate5m": "45.6K",
   "hashrate1hr": "54.8K",
   "hashrate1d": "56K",
   "hashrate7d": "53.6K",
   "lastshare": 1771992435,
   "shares": 740379.0,
   "bestshare": 1090.563420309137,
   "bestever": 1090.563420309137
  }
 ]
}
