{
 "hashrate1m": "59.7K",
 "hashrate5m": "42K",
 "hashrate1hr": "51.2K",
 "hashrate1d": "53.9K",
 "hashrate7d": "54.8K",
 "lastshare": 1761957006,
 "workers": 1,
 "shares": 619115.0,
 "bestshare": 1090.563420309137,
 "bestever": 1090.563420309137,
 "authorised": 1734028817,
 "worker": [
  {
   "workername": "[redacted]",
   "hashrate1m": "59.7K",
   "hashrate5m": "42K",
   "hashrate1hr": "51.2K",
   "hashrate1d": "53.9K",
   "hashrate7d": "54.8K",
   "lastshare": 1761957006,
   "shares": 619115.0,
   "bestshare": 1090.563420309137,
   "bestever": 1090.563420309137
  }
 ]
}
