{
 "hashrate1m": "17.5K",
 "hashrate5m": "44.2K",
 "hashrate1hr": "56.1K",
 "hashrate1d": "53K",
 "hashrate7d": "45.6K",
 "lastshare": 1758869429,
 "workers": 1,
 "shares": 580906.0,
 "bestshare": 1090.563420309137,
 "bestever": 1090.563420309137,
 "authorised": 1734028817,
 "worker": [
  {
   "workername": "[redacted]",
   "hashrate1m": "17.5K",
   "hashrate5m": "44.2K",
   "hashrate1hr": "56.1K",
   "hashrate1d": "53K",
   "hashrate7d": "45.6K",
   "lastshare": 1758869429,
   "shares": 580906.0,
   "bestshare": 1090.563420309137,
   "bestever": 1090.563420309137
  }
 ]
}
