{
 "hashrate1m": "113K",
 "hashrate5m": "86.8K",
 "hashrate1hr": "59.5K",
 "hashrate1d": "56.8K",
 "hashrate7d": "50.8K",
 "lastshare": 1760095918,
 "workers": 1,
 "shares": 595461.0,
 "bestshare": 1090.563420309137,
 "bestever": 1090.563420309137,
 "authorised": 1734028817,
 "worker": [
  {
   "workername": "[redacted]",
   "hashrate1m": "113K",
   "hashrate5m": "86.8K",
   "hashrate1hr": "59.5K",
   "hashrate1d": "56.8K",
   "hashrate7d": "50.8K",
   "lastshare": 1760095918,
   "shares": 595461.0,
   "bestshare": 1090.563420309137,
   "bestever": 1090.563420309137
  }
 ]
}
