{
 "hashrate1m": "57.6K",
 "hashrate5m": "56.2K",
 "hashrate1hr": "43.8K",
 "hashrate1d": "51K",
 "hashrate7d": "44.5K",
 "lastshare": 1758793689,
 "workers": 1,
 "shares": 579959.0,
 "bestshare": 1090.563420309137,
 "bestever": 1090.563420309137,
 "authorised": 1734028817,
 "worker": [
  {
   "workername": "[redacted]",
   "hashrate1m": "57.6K",
   "hashrate5m": "56.2K",
   "hashrate1hr": "43.8K",
   "hashrate1d": "51K",
   "hashrate7d": "44.5K",
   "lastshare": 1758793689,
   "shares": 579959.0,
   "bestshare": 1090.563420309137,
   "bestever": 1090.563420309137
  }
 ]
}
