{
 "hashrate1m": "44.7K",
 "hashrate5m": "40.5K",
 "hashrate1hr": "43.9K",
 "hashrate1d": "48.8K",
 "hashrate7d": "50.1K",
 "lastshare": 1756259859,
 "workers": 1,
 "shares": 532493.0,
 "bestshare": 1090.563420309137,
 "bestever": 1090.563420309137,
 "authorised": 1734028817,
 "worker": [
  {
   "workername": "[redacted]",
   "hashrate1m": "44.7K",
   "hashrate5m": "40.5K",
   "hashrate1hr": "43.9K",
   "hashrate1d": "48.8K",
   "hashrate7d": "50.1K",
   "lastshare": 1756259859,
   "shares": 532493.0,
   "bestshare": 1090.563420309137,
   "bestever": 1090.563420309137
  }
 ]
}
