{
 "hashrate1m": "69.6K",
 "hashrate5m": "44.1K",
 "hashrate1hr": "51K",
 "hashrate1d": "53.2K",
 "hashrate7d": "55.7K",
 "lastshare": 1766286689,
 "workers": 1,
 "shares": 676775.0,
 "bestshare": 1090.563420309137,
 "bestever": 1090.563420309137,
 "authorised": 1734028817,
 "worker": [
  {
   "workername": "[redacted]",
   "hashrate1m": "69.6K",
   "hashrate5m": "44.1K",
   "hashrate1hr": "51K",
   "hashrate1d": "53.2K",
   "hashrate7d": "55.7K",
   "lastshare": 1766286689,
   "shares": 676775.0,
   "bestshare": 1090.563420309137,
   "bestever": 1090.563420309137
  }
 ]
}
