{
 "hashrate1m": "178K",
 "hashrate5m": "96.6K",
 "hashrate1hr": "73.6K",
 "hashrate1d": "71.1K",
 "hashrate7d": "65.5K",
 "lastshare": 1764749253,
 "workers": 1,
 "shares": 655937.0,
 "bestshare": 1090.563420309137,
 "bestever": 1090.563420309137,
 "authorised": 1734028817,
 "worker": [
  {
   "workername": "[redacted]",
   "hashrate1m": "178K",
   "hashrate5m": "96.6K",
   "hashrate1hr": "73.6K",
   "hashrate1d": "71.1K",
   "hashrate7d": "65.5K",
   "lastshare": 1764749253,
   "shares": 655937.0,
   "bestshare": 1090.563420309137,
   "bestever": 1090.563420309137
  }
 ]
}
