{
 "hashrate1m": "46.5K",
 "hashrate5m": "52.6K",
 "hashrate1hr": "51.3K",
 "hashrate1d": "52K",
 "hashrate7d": "51.4K",
 "lastshare": 1753405644,
 "workers": 1,
 "shares": 467376.0,
 "bestshare": 1090.563420309137,
 "bestever": 1090.563420309137,
 "authorised": 1734028817,
 "worker": [
  {
   "workername": "[redacted]",
   "hashrate1m": "46.5K",
   "hashrate5m": "52.6K",
   "hashrate1hr": "51.3K",
   "hashrate1d": "52K",
   "hashrate7d": "51.4K",
   "lastshare": 1753405644,
   "shares": 467376.0,
   "bestshare": 1090.563420309137,
   "bestever": 1090.563420309137
  }
 ]
}
