{
 "hashrate1m": "46.7K",
 "hashrate5m": "59.5K",
 "hashrate1hr": "55.3K",
 "hashrate1d": "52.5K",
 "hashrate7d": "52.4K",
 "lastshare": 1771729633,
 "workers": 1,
 "shares": 736954.0,
 "bestshare": 1090.563420309137,
 "bestever": 1090.563420309137,
 "authorised": 1734028817,
 "worker": [
  {
   "workername": "[redacted]",
   "hashrate1m": "46.7K",
   "hashrate5m": "59.5K",
   "hashrate1hr": "55.3K",
   "hashrate1d": "52.5K",
   "hashrate7d": "52.4K",
   "lastshare": 1771729633,
   "shares": 736954.0,
   "bestshare": 1090.563420309137,
   "bestever": 1090.563420309137
  }
 ]
}
