{
 "hashrate1m": "176K",
 "hashrate5m": "101K",
 "hashrate1hr": "64.7K",
 "hashrate1d": "55.8K",
 "hashrate7d": "53.2K",
 "lastshare": 1768791975,
 "workers": 1,
 "shares": 702141.0,
 "bestshare": 1090.563420309137,
 "bestever": 1090.563420309137,
 "authorised": 1734028817,
 "worker": [
  {
   "workername": "[redacted]",
   "hashrate1m": "176K",
   "hashrate5m": "101K",
   "hashrate1hr": "64.7K",
   "hashrate1d": "55.8K",
   "hashrate7d": "53.2K",
   "lastshare": 1768791975,
   "shares": 702141.0,
   "bestshare": 1090.563420309137,
   "bestever": 1090.563420309137
  }
 ]
}
