{
 "hashrate1m": "75.8K",
 "hashrate5m": "59.3K",
 "hashrate1hr": "50.5K",
 "hashrate1d": "54.6K",
 "hashrate7d": "53.1K",
 "lastshare": 1763118794,
 "workers": 1,
 "shares": 633025.0,
 "bestshare": 1090.563420309137,
 "bestever": 1090.563420309137,
 "authorised": 1734028817,
 "worker": [
  {
   "workername": "[redacted]",
   "hashrate1m": "75.8K",
   "hashrate5m": "59.3K",
   "hashrate1hr": "50.5K",
   "hashrate1d": "54.6K",
   "hashrate7d": "53.1K",
   "lastshare": 1763118794,
   "shares": 633025.0,
   "bestshare": 1090.563420309137,
   "bestever": 1090.563420309137
  }
 ]
}
