{
 "hashrate1m": "137K",
 "hashrate5m": "91.6K",
 "hashrate1hr": "77.6K",
 "hashrate1d": "65.1K",
 "hashrate7d": "40.9K",
 "lastshare": 1751720120,
 "workers": 1,
 "shares": 424922.0,
 "bestshare": 1090.563420309137,
 "bestever": 1090.563420309137,
 "authorised": 1734028817,
 "worker": [
  {
   "workername": "[redacted]",
   "hashrate1m": "137K",
   "hashrate5m": "91.6K",
   "hashrate1hr": "77.6K",
   "hashrate1d": "65.1K",
   "hashrate7d": "40.9K",
   "lastshare": 1751720120,
   "shares": 424922.0,
   "bestshare": 1090.563420309137,
   "bestever": 1090.563420309137
  }
 ]
}
