{
 "hashrate1m": "45.4K",
 "hashrate5m": "44.5K",
 "hashrate1hr": "46.9K",
 "hashrate1d": "50.9K",
 "hashrate7d": "49.9K",
 "lastshare": 1755125576,
 "workers": 1,
 "shares": 505835.0,
 "bestshare": 1090.563420309137,
 "bestever": 1090.563420309137,
 "authorised": 1734028817,
 "worker": [
  {
   "workername": "[redacted]",
   "hashrate1m": "45.4K",
   "hashrate5m": "44.5K",
   "hashrate1hr": "46.9K",
   "hashrate1d": "50.9K",
   "hashrate7d": "49.9K",
   "lastshare": 1755125576,
   "shares": 505835.0,
   "bestshare": 1090.563420309137,
   "bestever": 1090.563420309137
  }
 ]
}
