{
 "hashrate1m": "25.5K",
 "hashrate5m": "32.6K",
 "hashrate1hr": "45.5K",
 "hashrate1d": "31.9K",
 "hashrate7d": "46K",
 "lastshare": 1753910356,
 "workers": 1,
 "shares": 477724.0,
 "bestshare": 1090.563420309137,
 "bestever": 1090.563420309137,
 "authorised": 1734028817,
 "worker": [
  {
   "workername": "[redacted]",
   "hashrate1m": "25.5K",
   "hashrate5m": "32.6K",
   "hashrate1hr": "45.5K",
   "hashrate1d": "31.9K",
   "hashrate7d": "46K",
   "lastshare": 1753910356,
   "shares": 477724.0,
   "bestshare": 1090.563420309137,
   "bestever": 1090.563420309137
  }
 ]
}
