{
 "hashrate1m": "42K",
 "hashrate5m": "46.4K",
 "hashrate1hr": "66.6K",
 "hashrate1d": "73.2K",
 "hashrate7d": "67.8K",
 "lastshare": 1764975256,
 "workers": 1,
 "shares": 659764.0,
 "bestshare": 1090.563420309137,
 "bestever": 1090.563420309137,
 "authorised": 1734028817,
 "worker": [
  {
   "workername": "[redacted]",
   "hashrate1m": "42K",
   "hashrate5m": "46.4K",
   "hashrate1hr": "66.6K",
   "hashrate1d": "73.2K",
   "hashrate7d": "67.8K",
   "lastshare": 1764975256,
   "shares": 659764.0,
   "bestshare": 1090.563420309137,
   "bestever": 1090.563420309137
  }
 ]
}
