{
 "hashrate1m": "127K",
 "hashrate5m": "75.4K",
 "hashrate1hr": "67.5K",
 "hashrate1d": "70K",
 "hashrate7d": "57.4K",
 "lastshare": 1764275480,
 "workers": 1,
 "shares": 647936.0,
 "bestshare": 1090.563420309137,
 "bestever": 1090.563420309137,
 "authorised": 1734028817,
 "worker": [
  {
   "workername": "[redacted]",
   "hashrate1m": "127K",
   "hashrate5m": "75.4K",
   "hashrate1hr": "67.5K",
   "hashrate1d": "70K",
   "hashrate7d": "57.4K",
   "lastshare": 1764275480,
   "shares": 647936.0,
   "bestshare": 1090.563420309137,
   "bestever": 1090.563420309137
  }
 ]
}
