{
 "hashrate1m": "12.1K",
 "hashrate5m": "23K",
 "hashrate1hr": "42.9K",
 "hashrate1d": "53K",
 "hashrate7d": "51.8K",
 "lastshare": 1768451125,
 "workers": 1,
 "shares": 697789.0,
 "bestshare": 1090.563420309137,
 "bestever": 1090.563420309137,
 "authorised": 1734028817,
 "worker": [
  {
   "workername": "[redacted]",
   "hashrate1m": "12.1K",
   "hashrate5m": "23K",
   "hashrate1hr": "42.9K",
   "hashrate1d": "53K",
   "hashrate7d": "51.8K",
   "lastshare": 1768451125,
   "shares": 697789.0,
   "bestshare": 1090.563420309137,
   "bestever": 1090.563420309137
  }
 ]
}
